README.md
setup.cfg
setup.py
varyaml.py
test/test_varyaml.py
varyaml.egg-info/PKG-INFO
varyaml.egg-info/SOURCES.txt
varyaml.egg-info/dependency_links.txt
varyaml.egg-info/requires.txt
varyaml.egg-info/top_level.txt