Metadata-Version: 2.1
Name: varyaml
Version: 0.0.4
Summary: yaml parser with environment interpolation -- safe secrets in configs
Home-page: https://github.com/abe-winter/varyaml
Author: Abe Winter
Author-email: awinter.public@gmail.com
License: MIT
Keywords: yaml environment config configuration
Platform: UNKNOWN
Classifier: Development Status :: 4 - Beta
Classifier: Intended Audience :: Developers
Classifier: License :: OSI Approved :: MIT License
Classifier: Programming Language :: Python :: 3.5
Provides-Extra: test
